Metadata-Version: 2.1
Name: hello-world-zenos
Version: 0.0.1
Summary: A hello-world example package
Home-page: https://httpbin.org
Author: Example Author
Author-email: author@example.com
License: UNKNOWN
Platform: UNKNOWN
Classifier: Programming Language :: Python :: 3
Classifier: License :: OSI Approved :: MIT License
Classifier: Operating System :: OS Independent
